{
  "type": "object",
  "properties": {
    "id_kiinteisto": {
      "type": "integer"
    },
    "kiinteistotunnus": {
      "type": "string",
      "maxLength": 255
    },
    "rakennuksets": {
      "type": "array",
      "items": {
        "$ref": "#/components/schemas/rakennukset"
      }
    },
    "rakennukset_fulls": {
      "type": "array",
      "items": {
        "$ref": "#/components/schemas/rakennukset_full"
      }
    }
  },
  "additionalProperties": false,
  "required": [
    "id_kiinteisto",
    "kiinteistotunnus"
  ]
}